<?xml version="1.0"?><patientBase><patient><name>Янчик</name><secondName>Кухальский</secondName><birthday>1999-05-05</birthday><healthy>false</healthy></patient><patient><name>Ян</name><secondName>Кухальский</secondName><birthday>1999-02-25</birthday><healthy>false</healthy></patient><patient><name>Вася</name><secondName>Пупкин</secondName><birthday>1990-01-01</birthday><healthy>true</healthy></patient><patient><name>Анна</name><secondName>Репетуева</secondName><birthday>2000-06-05</birthday><healthy>false</healthy></patient></patientBase>